PhotoTextSearcher/__init__.py
PhotoTextSearcher/test.py
PhotoTextSearcher/text_recognizer.py
phototextsearcher-0.1.4.dist-info/LICENSE
phototextsearcher-0.1.4.dist-info/METADATA
phototextsearcher-0.1.4.dist-info/WHEEL
phototextsearcher-0.1.4.dist-info/top_level.txt
phototextsearcher-0.1.4.dist-info/RECORD
