Metadata-Version: 2.2
Name: PhotoTextSearcher
Version: 0.1.4
Summary: Библиотека для распознавания текста на изображениях
Home-page: https://github.com/KinderModddins/PhotoTextSearcher
Author: MAKCNMOB
Author-email: support@modkey.fun
Classifier: Programming Language :: Python :: 3
Classifier: License :: OSI Approved :: MIT License
Classifier: Operating System :: OS Independent
Requires-Python: >=3.6
License-File: LICENSE
Requires-Dist: easyocr==1.7.2
Requires-Dist: Pillow
Requires-Dist: numpy
Dynamic: author
Dynamic: author-email
Dynamic: classifier
Dynamic: description
Dynamic: description-content-type
Dynamic: home-page
Dynamic: requires-dist
Dynamic: requires-python
Dynamic: summary
